fasterraster
