Metadata-Version: 2.1
Name: fasterraster
Version: 0.0.4
Summary: Fast multi-threaded raster operations with simple IO
Home-page: https://github.com/asenogles/fasterraster
Author: asenogles
License: BSD
Requires-Python: >=3.6
License-File: LICENSE
